rbox-0.1.4.dist-info/METADATA
rbox-0.1.4.dist-info/WHEEL
rbox/__init__.py
rbox/_rbox.cpython-310-x86_64-linux-gnu.so
rbox/_rbox.pyi
rbox/anlz.py
rbox/masterdb.py
rbox/models.py
rbox/rbxml.py
rbox/settings.py
rbox-0.1.4.dist-info/RECORD
