Metadata-Version: 2.4
Name: rbox
Version: 0.1.4
Classifier: Development Status :: 3 - Alpha
Classifier: Programming Language :: Python
Classifier: Programming Language :: Python :: 3
Classifier: Programming Language :: Python :: 3 :: Only
Classifier: Programming Language :: Python :: 3.9
Classifier: Programming Language :: Python :: 3.10
Classifier: Programming Language :: Python :: 3.11
Classifier: Programming Language :: Python :: 3.12
Classifier: Programming Language :: Python :: 3.13
Classifier: Programming Language :: Rust
Classifier: License :: OSI Approved :: MIT License
Classifier: License :: OSI Approved :: Apache Software License
Classifier: Operating System :: Microsoft :: Windows
Classifier: Operating System :: MacOS
Classifier: Operating System :: POSIX :: Linux
Classifier: Topic :: Database
Classifier: Topic :: Software Development :: Libraries
Classifier: Topic :: Software Development :: Libraries :: Python Modules
Classifier: Topic :: Database :: Database Engines/Servers
Requires-Dist: typing-extensions>=4.6.0,!=4.7.0
Requires-Dist: hypothesis>=6.0.0 ; extra == 'test'
Requires-Dist: pytest>=6.2.0 ; extra == 'test'
Requires-Dist: pytest-cov ; extra == 'test'
Requires-Dist: maturin ; extra == 'test'
Provides-Extra: test
Summary: Python library for interacting with the local and export data of Pioneers Rekordbox DJ software
Author-email: Dylan Jones <dylanljones@proton.me>
Requires-Python: >=3.9
Project-URL: Source, https://github.com/dylanljones/rbox
Project-URL: Tracker, https://github.com/dylanljones/rbox/issues
